vencode_sdk/__init__.py
vencode_sdk/api.py
vencode_sdk/client.py
vencode_sdk/options.py
vencode_sdk-0.0.1.dist-info/METADATA
vencode_sdk-0.0.1.dist-info/WHEEL
vencode_sdk-0.0.1.dist-info/top_level.txt
vencode_sdk-0.0.1.dist-info/RECORD
