Metadata-Version: 2.1
Name: vencode-sdk
Version: 0.0.1
Summary: Vencode API SDK wrapper for Python
Home-page: UNKNOWN
Author: Vencode
Author-email: hello@vencode.io
License: UNKNOWN
Keywords: python,video encoding,transcoding
Platform: UNKNOWN
Classifier: Development Status :: 3 - Alpha
Classifier: Intended Audience :: Education
Classifier: Programming Language :: Python :: 2
Classifier: Programming Language :: Python :: 3
Classifier: Operating System :: MacOS :: MacOS X
Classifier: Operating System :: Microsoft :: Windows
